heartsounds/__init__.py
heartsounds/align_audio.py
heartsounds/annotations.py
heartsounds/constants.py
heartsounds/find_agreed_points_runs.py
heartsounds/find_agreeing_points.py
heartsounds/find_ecg_peaks.py
heartsounds/find_heart_sound_locations.py
heartsounds/find_r_peaks.py
heartsounds/find_r_peaks_gqrs.py
heartsounds/find_r_peaks_neurokit2.py
heartsounds/find_r_peaks_xqrs.py
heartsounds/find_t_peak_ends.py
heartsounds/find_t_peak_ends_minima_gap.py
heartsounds/intervals.py
heartsounds/load_audio_data.py
heartsounds/load_ecg_data.py
HeartSounds-0.0.2.dist-info/LICENSE
HeartSounds-0.0.2.dist-info/METADATA
HeartSounds-0.0.2.dist-info/WHEEL
HeartSounds-0.0.2.dist-info/top_level.txt
HeartSounds-0.0.2.dist-info/RECORD
