Metadata-Version: 2.1
Name: HeartSounds
Version: 0.0.2
Summary: A package for automatically annotating heart sounds locations based on ECG traces.
Author: Jack Peck
Project-URL: Homepage, https://github.com/jackpeck/heartsounds
Project-URL: Bug Tracker, https://github.com/jackpeck/heartsounds/issues
Classifier: Programming Language :: Python :: 3
Classifier: License :: OSI Approved :: MIT License
Classifier: Operating System :: OS Independent
Requires-Python: >=3.7
License-File: LICENSE
